spssimage/__init__.py
spssimage/core.py
spssimage/tests.py
spssimage/utils.py
spssimage-0.1.5.dist-info/LICENSE
spssimage-0.1.5.dist-info/METADATA
spssimage-0.1.5.dist-info/WHEEL
spssimage-0.1.5.dist-info/top_level.txt
spssimage-0.1.5.dist-info/RECORD
