Metadata-Version: 2.2
Name: spssimage
Version: 0.1.5
Summary: A lightweight library for image creation and manipulation.
Home-page: https://github.com/Sumedh1599/spssimage
Author: Sumedh Patil
Author-email: sumedh.patil@aipresso.co.uk
Classifier: Programming Language :: Python :: 3
Classifier: License :: OSI Approved :: MIT License
Classifier: Operating System :: OS Independent
Requires-Python: >=3.6
License-File: LICENSE
Requires-Dist: numpy
Requires-Dist: Pillow
Dynamic: author
Dynamic: author-email
Dynamic: classifier
Dynamic: description
Dynamic: description-content-type
Dynamic: home-page
Dynamic: requires-dist
Dynamic: requires-python
Dynamic: summary
